sitejabber/__init__.py
sitejabber/utils.py
tests/__init__.py
tests/test_utils.py
sitejabber_utils-1.0.1.dist-info/LICENSE
sitejabber_utils-1.0.1.dist-info/METADATA
sitejabber_utils-1.0.1.dist-info/WHEEL
sitejabber_utils-1.0.1.dist-info/top_level.txt
sitejabber_utils-1.0.1.dist-info/RECORD
