Metadata-Version: 2.1
Name: sitejabber-utils
Version: 1.0.1
Summary: Library for user's payload encryption used with Sitejabber.
Home-page: https://github.com/sitejabber/python-utils
Author: Sitejabber
Author-email: support@sitejabber.com
License: MIT
Platform: UNKNOWN
Requires-Dist: pycryptodomex (>3.6.5)
